conmasd/__init__.py
conmasd/cli.py
conmasd/const.py
conmasd/main.py
conmasd/types/__init__.py
conmasd/types/conmasd_config/__init__.py
conmasd/types/conmasd_config/docker.py
conmasd/types/conmasd_config/github.py
conmasd/types/conmasd_config/main.py
conmasd/types/conmasd_config/runner.py
conmasd/types/container_info.py
conmasd/types/docker_container_status.py
conmasd/types/gh_entity.py
conmasd/types/runner_status.py
conmasd/util/__init__.py
conmasd/util/api/__init__.py
conmasd/util/api/docker.py
conmasd/util/api/github.py
conmasd/util/dict2liststr.py
conmasd/version.py
conmasd-0.1.4.dist-info/METADATA
conmasd-0.1.4.dist-info/WHEEL
conmasd-0.1.4.dist-info/entry_points.txt
conmasd-0.1.4.dist-info/RECORD
